multiples/__init__.py
multiples/is_multiple_of_five.py
multiples/is_multiple_of_two.py
multiple_math_library010111-0.1.0.dist-info/METADATA
multiple_math_library010111-0.1.0.dist-info/WHEEL
multiple_math_library010111-0.1.0.dist-info/top_level.txt
multiple_math_library010111-0.1.0.dist-info/RECORD
